best_first_search/__init__.py
best_first_search/heap.py
best_first_search/search.py
best_first_search/example/__init__.py
best_first_search/example/a_star.py
best_first_search-0.0.2.dist-info/LICENSE
best_first_search-0.0.2.dist-info/METADATA
best_first_search-0.0.2.dist-info/WHEEL
best_first_search-0.0.2.dist-info/top_level.txt
best_first_search-0.0.2.dist-info/RECORD
