Metadata-Version: 2.1
Name: best-first-search
Version: 0.0.2
Summary: My package description
Author: Han Jaeseung
Author-email: thestudentofkyoto@gmail.com
License: MIT License        
Keywords: best-first-search,graph-traversal
Classifier: Intended Audience :: Developers
Classifier: License :: OSI Approved :: MIT License
Classifier: Programming Language :: Python :: 3
Requires-Python: >=3.8
License-File: LICENSE
Provides-Extra: ci
Requires-Dist: pylint (==2.15.0) ; extra == 'ci'
Requires-Dist: mypy (<1.0) ; extra == 'ci'
Requires-Dist: setuptools-scm ; extra == 'ci'
Requires-Dist: pytest (<7.0.0) ; extra == 'ci'
Requires-Dist: isort (<6.0) ; extra == 'ci'
Requires-Dist: pytest-cov ; extra == 'ci'
Requires-Dist: codecov ; extra == 'ci'
Provides-Extra: example
Requires-Dist: networkx (>=2.8) ; extra == 'example'
Provides-Extra: visualize
Requires-Dist: matplotlib ; extra == 'visualize'
